aga_swarm/__init__.py
aga_swarm/actions/__init__.py
aga_swarm/actions/action_space_metadata.json
aga_swarm/actions/communication/__init__.py
aga_swarm/actions/data/__init__.py
aga_swarm/actions/data/cryptography/__init__.py
aga_swarm/actions/data/data_compression/__init__.py
aga_swarm/actions/data/data_preprocessing/__init__.py
aga_swarm/actions/data/data_transformations/__init__.py
aga_swarm/actions/data/data_validation/__init__.py
aga_swarm/actions/data/file_operations/__init__.py
aga_swarm/actions/data/file_operations/delete_file/__init__.py
aga_swarm/actions/data/file_operations/delete_file/delete_file.py
aga_swarm/actions/data/file_operations/delete_file/mac_delete_file.py
aga_swarm/actions/data/file_operations/move_file/__init__.py
aga_swarm/actions/data/file_operations/move_file/mac_move_file.py
aga_swarm/actions/data/file_operations/move_file/move_file.py
aga_swarm/actions/data/file_operations/rename_file/__init__.py
aga_swarm/actions/data/file_operations/rename_file/mac_rename_file.py
aga_swarm/actions/data/file_operations/rename_file/rename_file.py
aga_swarm/actions/data/file_operations/retrieve_file/__init__.py
aga_swarm/actions/data/file_operations/retrieve_file/mac_retrieve_file.py
aga_swarm/actions/data/file_operations/retrieve_file/retrieve_file.py
aga_swarm/actions/data/file_operations/upload_file/__init__.py
aga_swarm/actions/data/file_operations/upload_file/mac_upload_file.py
aga_swarm/actions/data/file_operations/upload_file/upload_file.py
aga_swarm/actions/data/folder_operations/__init__.py
aga_swarm/actions/data/folder_operations/delete_folder/__init__.py
aga_swarm/actions/data/folder_operations/delete_folder/delete_folder.py
aga_swarm/actions/data/folder_operations/delete_folder/mac_delete_folder.py
aga_swarm/actions/data/folder_operations/list_folder/__init__.py
aga_swarm/actions/data/folder_operations/list_folder/list_folder.py
aga_swarm/actions/data/folder_operations/list_folder/mac_list_folder.py
aga_swarm-0.1.2.dist-info/LICENSE
aga_swarm-0.1.2.dist-info/METADATA
aga_swarm-0.1.2.dist-info/WHEEL
aga_swarm-0.1.2.dist-info/RECORD
